lmquickbench/__init__.py
lmquickbench/cli.py
lmquickbench-0.1.0.dist-info/METADATA
lmquickbench-0.1.0.dist-info/WHEEL
lmquickbench-0.1.0.dist-info/entry_points.txt
lmquickbench-0.1.0.dist-info/top_level.txt
lmquickbench-0.1.0.dist-info/RECORD
