Metadata-Version: 2.1
Name: lmquickbench
Version: 0.1.0
Summary: A lightweight CLI tool to benchmark local LLMs running on LM Studio.
Home-page: https://github.com/yourusername/LMQuickBench
Author: Gordon Yeung
Requires-Python: >=3.7
Requires-Dist: requests
